mcp_gotify/__init__.py
mcp_gotify/config.py
mcp_gotify/main.py
mcp_gotify-0.1.1.dist-info/METADATA
mcp_gotify-0.1.1.dist-info/WHEEL
mcp_gotify-0.1.1.dist-info/entry_points.txt
mcp_gotify-0.1.1.dist-info/licenses/LICENSE
mcp_gotify-0.1.1.dist-info/RECORD
