Metadata-Version: 2.4
Name: mcp-gotify
Version: 0.1.1
Summary: MCP server for sending gotify notifications
Author-email: TerminalMan <84923604+SecretiveShell@users.noreply.github.com>
License-File: LICENSE
Requires-Python: >=3.13
Requires-Dist: fastmcp>=2.3.0
Requires-Dist: httpx>=0.28.1
Requires-Dist: mcp>=1.6.0
